README.md
crofter
setup.py
croft/__init__.py
croft.egg-info/PKG-INFO
croft.egg-info/SOURCES.txt
croft.egg-info/dependency_links.txt
croft.egg-info/top_level.txt
croft/datasource/__init__.py
croft/extensions/__init__.py
croft/primitive/__init__.py
croft/primitive/actor.py
croft/views/__init__.py
croft/views/quarto/__init__.py